pyaudiobookbinder/__init__.py
pyaudiobookbinder/pyaudiobookbinder.py
pyaudiobookbinder-0.7.1.dist-info/LICENSE
pyaudiobookbinder-0.7.1.dist-info/METADATA
pyaudiobookbinder-0.7.1.dist-info/WHEEL
pyaudiobookbinder-0.7.1.dist-info/entry_points.txt
pyaudiobookbinder-0.7.1.dist-info/top_level.txt
pyaudiobookbinder-0.7.1.dist-info/RECORD
