Metadata-Version: 2.1
Name: pyaudiobookbinder
Version: 0.7.1
Summary: PyAudioBookBinder is a lightweight tool using ffmeg which simplifies the process of binding multiple audio files togethers into an audiobook by gleaming smart defaults from the audio files's metadata, locations, durations, and names.
Author-email: Daniel Byrne <realdanielbyrne@icloud.com>
Project-URL: Homepage, https://github.com/realdanielbyrne/PyAudiobookBinder
Classifier: Intended Audience :: End Users/Desktop
Classifier: Intended Audience :: Developers
Classifier: Intended Audience :: Information Technology
Classifier: Development Status :: 4 - Beta
Classifier: Programming Language :: Python
Classifier: Operating System :: OS Independent
Classifier: Programming Language :: Python :: 3.9
Classifier: License :: OSI Approved :: MIT License
Requires-Python: >=3.9.0
License-File: LICENSE
Requires-Dist: argparse
